Metadata-Version: 1.1
Name: ady
Version: 0.3
Summary: ADY - Schedule between Baku Sumgait Baku
Home-page: https://github.com/Chingiz/ADY-Hereket-Cedveli
Author: Chingiz Huseynzade
Author-email: chingiz.h@gmail.com
License: UNKNOWN
Download-URL: https://github.com/Chingiz/ADY-Hereket-Cedveli/archive/0.3.tar.gz
Keywords: ady,schedule,baku,sumgait
Platform: UNKNOWN
